mrmuscle/__init__.py
mrmuscle-0.0.0.dist-info/METADATA
mrmuscle-0.0.0.dist-info/WHEEL
mrmuscle-0.0.0.dist-info/top_level.txt
mrmuscle-0.0.0.dist-info/RECORD
