Metadata-Version: 2.4
Name: mrmuscle
Version: 0.0.0
Summary: Package for post-processing analysis of skeletal muscle magnetic resonance imaging data. Coming soon
Author-email: Susanne Rauh <s.s.rauh@lumc.nl>, Donnie Cameron <donniecameron.09@gmail.com>, Candace Makeda Moore <doctormakeda@gmail.com>
